cmonitor/__init__.py
cmonitor/cli.py
cmonitor/manager.py
cmonitor/scraper.py
cmonitor/socket_tools.py
craigslist_monitor-0.1.7.dist-info/DESCRIPTION.rst
craigslist_monitor-0.1.7.dist-info/METADATA
craigslist_monitor-0.1.7.dist-info/RECORD
craigslist_monitor-0.1.7.dist-info/WHEEL
craigslist_monitor-0.1.7.dist-info/entry_points.txt
craigslist_monitor-0.1.7.dist-info/metadata.json
craigslist_monitor-0.1.7.dist-info/top_level.txt
