Metadata-Version: 2.0
Name: craigslist-monitor
Version: 0.1.7
Summary: A monitor for craigslist searches.
Home-page: https://github.com/FilipOsowski/craigslist-monitor
Author: Filip Osowski
Author-email: filiposowski5@gmail.com
License: MIT
Platform: UNKNOWN
Classifier: Development Status :: 3 - Alpha
Classifier: Programming Language :: Python :: 3
Requires-Python: ~=3.0
Requires-Dist: python-daemon (>=2.0.0)
Requires-Dist: requests (>=2.0.0)
Requires-Dist: lxml (>=4.0.0)
